prj_cpu/mem.v
module mem
(
    //时钟复位
    input wire sys_clk,
    input wire sys_rst,
    //输入输出
    input wire sys_ctr,//状态控制，1有效
    input wire sys_io,//方向控制，0保存、1读取
    output reg sys_done,//操作完成，1有效
    input wire[31:0]sys_data_addr,//操作地址
    output reg[31:0]sys_data_rd,//读取数据
    input wire[31:0]sys_data_sv//保存数据
);

//状态机
parameter[1:0]MOD_STATE_WORK=1;
parameter[1:0]MOD_STATE_DONE=2;
reg[1:0]mod_state;
//寄存器组
reg[31:0]mod_reg[0:31];

//逻辑实现
always@(posedge sys_clk or negedge sys_rst)
begin
    //复位
    if(!sys_rst)
    begin
        mod_reg[0]<=0;
        mod_reg[1]<=0;
        mod_reg[2]<=0;
        mod_reg[3]<=0;
        mod_reg[4]<=0;
        mod_reg[5]<=0;
        mod_reg[6]<=0;
        mod_reg[7]<=0;
        mod_reg[8]<=0;
        mod_reg[9]<=0;
        mod_reg[10]<=0;
        mod_reg[11]<=0;
        mod_reg[12]<=0;
        mod_reg[13]<=0;
        mod_reg[14]<=0;
        mod_reg[15]<=0;
        mod_reg[16]<=0;
        mod_reg[17]<=0;
        mod_reg[18]<=0;
        mod_reg[19]<=0;
        mod_reg[20]<=0;
        mod_reg[21]<=0;
        mod_reg[22]<=0;
        mod_reg[23]<=0;
        mod_reg[24]<=0;
        mod_reg[25]<=0;
        mod_reg[26]<=0;
        mod_reg[27]<=0;
        mod_reg[28]<=0;
        mod_reg[29]<=0;
        mod_reg[30]<=0;
        mod_reg[31]<=0;
        mod_state<=MOD_STATE_DONE;
        sys_data_rd<=0;
        sys_done<=1;
    end
    //功能
    else
    begin
        case(mod_state)
            //空闲
            MOD_STATE_DONE:
            begin
                mod_state<=MOD_STATE_DONE;
            end
            //读写
            MOD_STATE_WORK:
            begin
                //判断方向
                case(sys_io)
                    //保存
                    0:
                    begin
                        mod_reg[sys_data_addr]<=sys_data_sv;
                    end
                    //读取
                    1:
                    begin
                        sys_data_rd<=mod_reg[sys_data_addr];
                    end
                endcase
                mod_state<=MOD_STATE_DONE;
            end
            //错误
            default:
            begin
                mod_state<=MOD_STATE_DONE;
            end
        endcase
    end
end

//触发
always@(posedge sys_ctr)
begin
    mod_state<=MOD_STATE_WORK;
end

//输出
always@(*)
begin
    if(mod_state==MOD_STATE_DONE)
    begin
        sys_done=1;
    end
    else
    begin
        sys_done=0;
    end
end

endmodule

prj_cpu/cpu.v
module cpu
(
    //时钟复位
    input wire sys_clk,
    input wire sys_rst,
    //指令
    input wire[31:0]sys_inst_cmd,//指令字节
    input wire sys_inst_up,//指令更新，上升沿有效
    output reg sys_inst_st,//指令状态，1完成
    //输入输出
    output reg sys_io_ctr,//状态控制，1有效
    output reg sys_io_io,//方向控制，0保存、1读取
    input wire sys_io_done,//操作完成，1有效
    output reg[31:0]sys_io_data_addr,//操作地址
    input wire[31:0]sys_io_data_rd,//读取数据
    output reg[31:0]sys_io_data_sv,//保存数据
    //调试输出
    output wire[31:0]sys_cpu_reg0,
    output wire[31:0]sys_cpu_reg1,
    output wire[31:0]sys_cpu_reg2,
    output wire[31:0]sys_cpu_reg3
);

//状态机
reg[3:0]mod_state;
localparam MOD_STATE_WORK=1;//工作
localparam MOD_STATE_WAIT_1=2;//等待阶段1
localparam MOD_STATE_ERROR=3;//错误
localparam MOD_STATE_DONE=4;//完成
//寄存器组
reg[31:0]mod_reg[0:31];

//指令字段
wire[3:0]mod_opcd_0=sys_inst_cmd[31:28];//操作码0
wire[5:0]mod_opcd_1=sys_inst_cmd[27:22];//操作码1
wire[4:0]mod_opreg_0=sys_inst_cmd[21:17];//操作寄存器0
wire[4:0]mod_opreg_1=sys_inst_cmd[16:12];//操作寄存器1
wire[4:0]mod_opreg_2=sys_inst_cmd[11:7];//操作寄存器2
wire[4:0]mod_opreg_3=sys_inst_cmd[6:2];//操作寄存器3
wire[1:0]mod_opext_0=sys_inst_cmd[1:0];//操作扩展0

//基本指令集
localparam MOD_INST_BAS=1;
localparam MOD_INST_BAS_AND=1;//与
localparam MOD_INST_BAS_OR=2;//或
localparam MOD_INST_BAS_NOT=3;//非
localparam MOD_INST_BAS_XOR=4;//异或
localparam MOD_INST_BAS_CP=5;//复制
localparam MOD_INST_BAS_MVL=6;//左移
localparam MOD_INST_BAS_MVR=7;//右移
localparam MOD_INST_BAS_LD=8;//加载立即数
//输入输出指令集
localparam MOD_INST_IO=2;
localparam MOD_INST_IO_READ=1;//读取
localparam MOD_INST_IO_SAVE=2;//保存
//数学运算指令集
localparam MOD_INST_MC=3;
localparam MOD_INST_MC_ADD=1;//加
localparam MOD_INST_MC_SUB=2;//减
localparam MOD_INST_MC_BGT=3;//大于
localparam MOD_INST_MC_EQ=4;//等于
localparam MOD_INST_MC_LST=5;//小于

//调试输出连接
assign sys_cpu_reg0=mod_reg[0];
assign sys_cpu_reg1=mod_reg[1];
assign sys_cpu_reg2=mod_reg[2];
assign sys_cpu_reg3=mod_reg[3];

//指令处理
always@(posedge sys_clk or negedge sys_rst)
begin
    //复位
    if(!sys_rst)
    begin
        //初始化寄存器
        mod_reg[0]<=0;
        mod_reg[1]<=0;
        mod_reg[2]<=0;
        mod_reg[3]<=0;
        mod_reg[4]<=0;
        mod_reg[5]<=0;
        mod_reg[6]<=0;
        mod_reg[7]<=0;
        mod_reg[8]<=0;
        mod_reg[9]<=0;
        mod_reg[10]<=0;
        mod_reg[11]<=0;
        mod_reg[12]<=0;
        mod_reg[13]<=0;
        mod_reg[14]<=0;
        mod_reg[15]<=0;
        mod_reg[16]<=0;
        mod_reg[17]<=0;
        mod_reg[18]<=0;
        mod_reg[19]<=0;
        mod_reg[20]<=0;
        mod_reg[21]<=0;
        mod_reg[22]<=0;
        mod_reg[23]<=0;
        mod_reg[24]<=0;
        mod_reg[25]<=0;
        mod_reg[26]<=0;
        mod_reg[27]<=0;
        mod_reg[28]<=0;
        mod_reg[29]<=0;
        mod_reg[30]<=0;
        mod_reg[31]<=0;
        //状态机
        mod_state<=MOD_STATE_DONE;
        //输入输出
        sys_io_ctr<=0;
        sys_io_io<=0;
        sys_io_data_addr<=0;
        sys_io_data_sv<=0;
        //状态
        sys_inst_st<=1;
    end
    //处理
    else
    begin
        //判断状态
        case(mod_state)
            //空闲
            MOD_STATE_DONE:
            begin
                mod_state<=MOD_STATE_DONE;
            end
            //工作
            MOD_STATE_WORK,MOD_STATE_WAIT_1:
            begin
                //操作码0
                case(mod_opcd_0)
                    //基本指令集
                    MOD_INST_BAS:
                    begin
                        //操作码1
                        case(mod_opcd_1)
                            //与
                            MOD_INST_BAS_AND:
                            begin
                                mod_reg[mod_opreg_0]<=mod_reg[mod_opreg_1]&mod_reg[mod_opreg_2];
                                mod_state<=MOD_STATE_DONE;
                            end
                            //或
                            MOD_INST_BAS_OR:
                            begin
                                mod_reg[mod_opreg_0]<=mod_reg[mod_opreg_1]|mod_reg[mod_opreg_2];
                                mod_state<=MOD_STATE_DONE;
                            end
                            //非
                            MOD_INST_BAS_NOT:
                            begin
                                mod_reg[mod_opreg_0]<=~mod_reg[mod_opreg_1];
                                mod_state<=MOD_STATE_DONE;
                            end
                            //异或
                            MOD_INST_BAS_XOR:
                            begin
                                mod_reg[mod_opreg_0]<=mod_reg[mod_opreg_1]^mod_reg[mod_opreg_2];
                                mod_state<=MOD_STATE_DONE;
                            end
                            //复制
                            MOD_INST_BAS_CP:
                            begin
                                mod_reg[mod_opreg_0]<=mod_reg[mod_opreg_1];
                                mod_state<=MOD_STATE_DONE;
                            end
                            //左移
                            MOD_INST_BAS_MVL:
                            begin
                                // mod_reg[mod_opreg_0]<=mod_reg[mod_opreg_1]<<mod_opreg_1;
                                mod_reg[mod_opreg_0]<=mod_reg[mod_opreg_1]<<mod_reg[mod_opreg_2];
                                mod_state<=MOD_STATE_DONE;
                            end
                            //右移
                            MOD_INST_BAS_MVR:
                            begin
                                // mod_reg[mod_opreg_0]<=mod_reg[mod_opreg_1]>>mod_opreg_1;
                                mod_reg[mod_opreg_0]<=mod_reg[mod_opreg_1]>>mod_reg[mod_opreg_2];
                                mod_state<=MOD_STATE_DONE;
                            end
                            //加载立即数
                            MOD_INST_BAS_LD:
                            begin
                                mod_reg[mod_opreg_0]<=sys_inst_cmd[16:0];
                                mod_state<=MOD_STATE_DONE;
                            end
                            //未知
                            default:
                            begin
                                mod_state<=MOD_STATE_ERROR;
                            end
                        endcase
                    end
                    //输入输出指令集
                    MOD_INST_IO:
                    begin
                        //操作码1
                        case(mod_opcd_1)
                            //读取
                            MOD_INST_IO_READ:
                            begin
                                case(mod_state)
                                    //发起
                                    MOD_STATE_WORK:
                                    begin
                                        sys_io_data_addr<=mod_reg[mod_opreg_1];
                                        sys_io_io<=1;
                                        sys_io_ctr<=1;
                                        mod_state<=MOD_STATE_WAIT_1;
                                    end
                                    //等待
                                    MOD_STATE_WAIT_1:
                                    begin
                                        if(sys_io_done)
                                        begin
                                            mod_reg[mod_opreg_0]<=sys_io_data_rd;
                                            sys_io_ctr<=0;
                                            mod_state<=MOD_STATE_DONE;
                                        end
                                    end
                                    //未知
                                    default:
                                    begin
                                        mod_state<=MOD_STATE_ERROR;
                                    end                        
                                endcase
                            end
                            //保存
                            MOD_INST_IO_SAVE:
                            begin
                                case(mod_state)
                                    //发起
                                    MOD_STATE_WORK:
                                    begin
                                        sys_io_data_addr<=mod_reg[mod_opreg_1];
                                        sys_io_data_sv<=mod_reg[mod_opreg_0];
                                        sys_io_io<=0;
                                        sys_io_ctr<=1;
                                        mod_state<=MOD_STATE_WAIT_1;
                                    end
                                    //等待
                                    MOD_STATE_WAIT_1:
                                    begin
                                        if(sys_io_done)
                                        begin
                                            sys_io_ctr<=0;
                                            mod_state<=MOD_STATE_DONE;
                                        end
                                    end
                                    //未知
                                    default:
                                    begin
                                        mod_state<=MOD_STATE_ERROR;
                                    end                        
                                endcase
                            end
                            //未知
                            default:
                            begin
                                mod_state<=MOD_STATE_ERROR;
                            end
                        endcase
                    end
                    //未知
                    default:
                    begin
                        mod_state<=MOD_STATE_ERROR;
                    end
                endcase
            end
        endcase
    end
end


//触发
always@(posedge sys_inst_up)
begin
    mod_state<=MOD_STATE_WORK;
end

//输出
always@(*)
begin
    if(mod_state==MOD_STATE_DONE)
    begin
        sys_inst_st=1;
    end
    else
    begin
        sys_inst_st=0;
    end
end


endmodule

prj_cpu/top_test_cpu.v

`timescale 1ns/1ps
module top_test_cpu();
    //计数器
    reg[31:0]sys_count;
    //端口
    reg sys_clk;
    reg sys_rst;
    //实例化CPU
    reg[31:0]cpu_inst_cmd;
    reg cpu_inst_up;
    wire cpu_inst_st;
    wire cpu_io_ctr;
    wire cpu_io_io;
    reg cpu_io_done;
    wire[31:0]cpu_io_data_addr;
    reg[31:0]cpu_io_data_rd;
    wire[31:0]cpu_io_data_sv;
    wire[31:0]cpu_cpu_reg0;
    wire[31:0]cpu_cpu_reg1;
    wire[31:0]cpu_cpu_reg2;
    wire[31:0]cpu_cpu_reg3;
    cpu
    u_cpu(
        .sys_clk          	(sys_clk           ),
        .sys_rst          	(sys_rst           ),
        .sys_inst_cmd     	(cpu_inst_cmd      ),
        .sys_inst_up      	(cpu_inst_up       ),
        .sys_inst_st      	(cpu_inst_st       ),
        .sys_io_ctr       	(cpu_io_ctr        ),
        .sys_io_io        	(cpu_io_io         ),
        .sys_io_done      	(cpu_io_done       ),
        .sys_io_data_addr 	(cpu_io_data_addr  ),
        .sys_io_data_rd   	(cpu_io_data_rd    ),
        .sys_io_data_sv   	(cpu_io_data_sv    ),
        .sys_cpu_reg0     	(cpu_cpu_reg0      ),
        .sys_cpu_reg1     	(cpu_cpu_reg1      ),
        .sys_cpu_reg2     	(cpu_cpu_reg2      ),
        .sys_cpu_reg3     	(cpu_cpu_reg3      )
    );
    //实例化MEM
    reg mem_ctr;
    reg mem_io;
    wire mem_done;
    reg[31:0]mem_data_addr;
    wire[31:0]mem_data_rd;
    reg[31:0]mem_data_sv;
    mem
    u_mem(
        .sys_clk     	(sys_clk      ),
        .sys_rst     	(sys_rst      ),
        .sys_ctr     	(mem_ctr      ),
        .sys_io      	(mem_io       ),
        .sys_done    	(mem_done     ),
        .sys_data_addr  (mem_data_addr),
        .sys_data_rd 	(mem_data_rd  ),
        .sys_data_sv 	(mem_data_sv  )
    );
    //连接
    assign mem_ctr        = cpu_io_ctr;
    assign mem_io         = cpu_io_io;
    assign mem_data_addr  = cpu_io_data_addr;
    assign mem_data_sv    = cpu_io_data_sv;
    assign cpu_io_done    = mem_done;
    assign cpu_io_data_rd = mem_data_rd;


    //时钟
    always
    begin
        #10;
        sys_clk=~sys_clk;
    end

    //功能
    initial
    begin
        //初始化
        $display("end simulate");
        $dumpfile("top_test_cpu.vcd");
        $dumpvars(0,top_test_cpu);
        $display("start simulate");
        //复位
        sys_rst=1;
        #1
        sys_rst=0;
        #1
        sys_rst=1;
        sys_clk=0;
        sys_count=0;
        #10
        sys_count=10;

        //等待执行完毕
        #1
        wait(sys_clk==1);
        wait(cpu_inst_st==1);
        //加载立即数到寄存器0
        cpu_inst_cmd={4'd1,6'd8,5'd0,17'd17};
        cpu_inst_up=0;
        cpu_inst_up=1;
        sys_count=sys_count+1;

        //等待执行完毕
        #1
        wait(sys_clk==1);
        wait(cpu_inst_st==1);
        //保存数据到内存0
        cpu_inst_cmd={4'd2,6'd2,5'd0,5'd0,12'd0};
        cpu_inst_up=0;
        cpu_inst_up=1;
        sys_count=sys_count+1;

        //等待执行完毕
        #1
        wait(sys_clk==1);
        wait(cpu_inst_st==1);
        //读取内存0到寄存器1
        cpu_inst_cmd={4'd2,6'd1,5'd1,5'd0,12'd0};
        cpu_inst_up=0;
        cpu_inst_up=1;
        sys_count=sys_count+1;

        //等待执行完毕
        #1
        // $display("sys_clk=%b",sys_clk);
        wait(sys_clk==1);
        // $display("cpu_inst_st=%b",cpu_inst_st);
        wait(cpu_inst_st==1);
        //结束
        sys_count=sys_count+10;
        #40;
        $display("end simulate");
        $finish;
    end

endmodule







// `timescale 1ns/1ps
// module top_test_cpu();
//     //计数器
//     reg[31:0]sys_count;
//     //端口
//     reg sys_clk;
//     reg sys_rst;
//     reg[31:0]cpu_inst_cmd;
//     reg cpu_inst_up;
//     wire cpu_inst_st;
//     wire cpu_io_ctr;
//     wire cpu_io_io;
//     reg cpu_io_done;
//     wire[31:0]cpu_io_data_addr;
//     reg[31:0]cpu_io_data_rd;
//     wire[31:0]cpu_io_data_sv;
//     wire[31:0]cpu_cpu_reg0;
//     wire[31:0]cpu_cpu_reg1;
//     wire[31:0]cpu_cpu_reg2;
//     wire[31:0]cpu_cpu_reg3;
//     //实例化CPU
//     cpu
//     u_cpu(
//         .sys_clk          	(sys_clk           ),
//         .sys_rst          	(sys_rst           ),
//         .sys_inst_cmd     	(cpu_inst_cmd      ),
//         .sys_inst_up      	(cpu_inst_up       ),
//         .sys_inst_st      	(cpu_inst_st       ),
//         .sys_io_ctr       	(cpu_io_ctr        ),
//         .sys_io_io        	(cpu_io_io         ),
//         .sys_io_done      	(cpu_io_done       ),
//         .sys_io_data_addr 	(cpu_io_data_addr  ),
//         .sys_io_data_rd   	(cpu_io_data_rd    ),
//         .sys_io_data_sv   	(cpu_io_data_sv    ),
//         .sys_cpu_reg0     	(cpu_cpu_reg0      ),
//         .sys_cpu_reg1     	(cpu_cpu_reg1      ),
//         .sys_cpu_reg2     	(cpu_cpu_reg2      ),
//         .sys_cpu_reg3     	(cpu_cpu_reg3      )
//     );
    
//     //时钟
//     always
//     begin
//         #10;
//         sys_clk=~sys_clk;
//     end

//     //功能
//     initial
//     begin
//         //初始化
//         $display("end simulate");
//         $dumpfile("top_test_cpu.vcd");
//         $dumpvars(0,top_test_cpu);
//         $display("start simulate");
//         //复位
//         sys_rst=1;
//         #1
//         sys_rst=0;
//         #1
//         sys_rst=1;
//         sys_clk=0;
//         sys_count=0;
//         #30
//         sys_count=sys_count+10;



//         //等待执行完毕
//         #1
//         wait(sys_clk==1);
//         // $display("cpu_inst_st=%b",cpu_inst_st);
//         wait(cpu_inst_st==1);
//         //加载立即数到寄存器0
//         cpu_inst_cmd={4'b0001,6'b1001,5'd0,17'd17};
//         cpu_inst_up=0;
//         cpu_inst_up=1;
//         sys_count=sys_count+1;


//         //等待执行完毕
//         #1
//         $display("sys_clk=%b",sys_clk);
//         wait(sys_clk==1);
//         $display("cpu_inst_st=%b",cpu_inst_st);
//         wait(cpu_inst_st==1);
//         //加载立即数到寄存器0
//         cpu_inst_cmd={4'b0001,6'b1001,5'd0,17'd8};
//         cpu_inst_up=0;
//         cpu_inst_up=1;
//         sys_count=sys_count+1;


//         //等待执行完毕
//         #1
//         $display("sys_clk=%b",sys_clk);
//         wait(sys_clk==1);
//         $display("cpu_inst_st=%b",cpu_inst_st);
//         wait(cpu_inst_st==1);
//         //寄存器左移
//         cpu_inst_cmd={4'b0001,6'b0110,5'd0,5'd0,5'd0,5'd0,2'd0};
//         cpu_inst_up=0;
//         cpu_inst_up=1;
//         sys_count=sys_count+1;


//         //等待执行完毕
//         #1
//         $display("sys_clk=%b",sys_clk);
//         wait(sys_clk==1);
//         $display("cpu_inst_st=%b",cpu_inst_st);
//         wait(cpu_inst_st==1);
//         //结束
//         sys_count=sys_count+10;
//         #30;
//         $display("end simulate");
//         $finish;
//     end

// endmodule

prj_cpu/top_test_cpu.vcd
$date
	Sun Jun 29 12:16:47 2025
$end
$version
	Icarus Verilog
$end
$timescale
	1ps
$end
$scope module top_test_cpu $end
$var wire 32 ! cpu_io_data_rd [31:0] $end
$var wire 1 " cpu_io_done $end
$var wire 1 # mem_ctr $end
$var wire 32 $ mem_data_addr [31:0] $end
$var wire 32 % mem_data_sv [31:0] $end
$var wire 1 & mem_io $end
$var wire 1 ' mem_done $end
$var wire 32 ( mem_data_rd [31:0] $end
$var wire 1 ) cpu_io_io $end
$var wire 32 * cpu_io_data_sv [31:0] $end
$var wire 32 + cpu_io_data_addr [31:0] $end
$var wire 1 , cpu_io_ctr $end
$var wire 1 - cpu_inst_st $end
$var wire 32 . cpu_cpu_reg3 [31:0] $end
$var wire 32 / cpu_cpu_reg2 [31:0] $end
$var wire 32 0 cpu_cpu_reg1 [31:0] $end
$var wire 32 1 cpu_cpu_reg0 [31:0] $end
$var reg 32 2 cpu_inst_cmd [31:0] $end
$var reg 1 3 cpu_inst_up $end
$var reg 1 4 sys_clk $end
$var reg 32 5 sys_count [31:0] $end
$var reg 1 6 sys_rst $end
$scope module u_cpu $end
$var wire 1 4 sys_clk $end
$var wire 32 7 sys_cpu_reg0 [31:0] $end
$var wire 32 8 sys_cpu_reg1 [31:0] $end
$var wire 32 9 sys_cpu_reg2 [31:0] $end
$var wire 32 : sys_cpu_reg3 [31:0] $end
$var wire 32 ; sys_inst_cmd [31:0] $end
$var wire 1 3 sys_inst_up $end
$var wire 32 < sys_io_data_rd [31:0] $end
$var wire 1 " sys_io_done $end
$var wire 1 6 sys_rst $end
$var wire 5 = mod_opreg_3 [4:0] $end
$var wire 5 > mod_opreg_2 [4:0] $end
$var wire 5 ? mod_opreg_1 [4:0] $end
$var wire 5 @ mod_opreg_0 [4:0] $end
$var wire 2 A mod_opext_0 [1:0] $end
$var wire 6 B mod_opcd_1 [5:0] $end
$var wire 4 C mod_opcd_0 [3:0] $end
$var parameter 32 D MOD_INST_BAS $end
$var parameter 32 E MOD_INST_BAS_AND $end
$var parameter 32 F MOD_INST_BAS_CP $end
$var parameter 32 G MOD_INST_BAS_LD $end
$var parameter 32 H MOD_INST_BAS_MVL $end
$var parameter 32 I MOD_INST_BAS_MVR $end
$var parameter 32 J MOD_INST_BAS_NOT $end
$var parameter 32 K MOD_INST_BAS_OR $end
$var parameter 32 L MOD_INST_BAS_XOR $end
$var parameter 32 M MOD_INST_IO $end
$var parameter 32 N MOD_INST_IO_READ $end
$var parameter 32 O MOD_INST_IO_SAVE $end
$var parameter 32 P MOD_INST_MC $end
$var parameter 32 Q MOD_INST_MC_ADD $end
$var parameter 32 R MOD_INST_MC_BGT $end
$var parameter 32 S MOD_INST_MC_EQ $end
$var parameter 32 T MOD_INST_MC_LST $end
$var parameter 32 U MOD_INST_MC_SUB $end
$var parameter 32 V MOD_STATE_DONE $end
$var parameter 32 W MOD_STATE_ERROR $end
$var parameter 32 X MOD_STATE_WAIT_1 $end
$var parameter 32 Y MOD_STATE_WORK $end
$var reg 4 Z mod_state [3:0] $end
$var reg 1 - sys_inst_st $end
$var reg 1 , sys_io_ctr $end
$var reg 32 [ sys_io_data_addr [31:0] $end
$var reg 32 \ sys_io_data_sv [31:0] $end
$var reg 1 ) sys_io_io $end
$upscope $end
$scope module u_mem $end
$var wire 1 4 sys_clk $end
$var wire 1 # sys_ctr $end
$var wire 32 ] sys_data_addr [31:0] $end
$var wire 32 ^ sys_data_sv [31:0] $end
$var wire 1 & sys_io $end
$var wire 1 6 sys_rst $end
$var parameter 2 _ MOD_STATE_DONE $end
$var parameter 2 ` MOD_STATE_WORK $end
$var reg 2 a mod_state [1:0] $end
$var reg 32 b sys_data_rd [31:0] $end
$var reg 1 ' sys_done $end
$upscope $end
$upscope $end
$enddefinitions $end
$comment Show the parameter values. $end
$dumpall
b1 `
b10 _
b1 Y
b10 X
b11 W
b100 V
b10 U
b101 T
b100 S
b11 R
b1 Q
b11 P
b10 O
b1 N
b10 M
b100 L
b10 K
b11 J
b111 I
b110 H
b1000 G
b101 F
b1 E
b1 D
$end
#0
$dumpvars
bx b
bx a
bx ^
bx ]
bx \
bx [
bx Z
bx C
bx B
bx A
bx @
bx ?
bx >
bx =
bx <
bx ;
bx :
bx 9
bx 8
bx 7
16
bx 5
x4
x3
bx 2
bx 1
bx 0
bx /
bx .
x-
x,
bx +
bx *
x)
bx (
x'
x&
bx %
bx $
x#
x"
bx !
$end
#1000
1-
b0 %
b0 ^
b0 *
b0 \
b0 $
b0 ]
b0 +
b0 [
0&
0)
0#
0,
b100 Z
b0 .
b0 :
b0 /
b0 9
b0 0
b0 8
b0 1
b0 7
1"
1'
b0 !
b0 <
b0 (
b0 b
b10 a
06
#2000
b0 5
04
16
#10000
14
#12000
b1010 5
#13000
0-
b1 Z
b1 C
b1000 B
b0 @
b0 ?
b0 >
b100 =
b1 A
b1011 5
13
b10010000000000000000000010001 2
b10010000000000000000000010001 ;
#20000
04
#30000
b10 C
b10 B
b0 =
b0 A
b1100 5
13
b100000100000000000000000000000 2
b100000100000000000000000000000 ;
0-
b1 Z
b10001 1
b10001 7
14
#40000
04
#50000
0"
0'
b1 a
b10 Z
1#
1,
b10001 %
b10001 ^
b10001 *
b10001 \
b10001 $
b10001 ]
b10001 +
b10001 [
14
#60000
04
#70000
1"
1'
b10 a
14
#80000
04
#90000
b1 B
b1 @
b1101 5
13
b100000010000100000000000000000 2
b100000010000100000000000000000 ;
0-
b1 Z
0#
0,
14
#100000
04
#110000
0"
0'
b1 a
b10 Z
1#
1,
1&
1)
14
#120000
04
#130000
1"
1'
b10 a
b10001 !
b10001 <
b10001 (
b10001 b
14
#140000
04
#150000
b10111 5
1-
b100 Z
0#
0,
b10001 0
b10001 8
14
